.class final enum Lo/pi$Ą;
.super Ljava/lang/Enum;
.source ""


# annotations
.annotation system Ldalvik/annotation/EnclosingClass;
    value = Lo/pi;
.end annotation

.annotation system Ldalvik/annotation/InnerClass;
    accessFlags = 0x4018
    name = "\u0104"
.end annotation

.annotation system Ldalvik/annotation/Signature;
    value = {
        "Ljava/lang/Enum<Lo/pi$\u0104;>;"
    }
.end annotation


# static fields
.field public static final enum Ą:Lo/pi$Ą;

.field public static final enum ą:Lo/pi$Ą;

.field public static final enum Ć:Lo/pi$Ą;

.field public static final enum ć:Lo/pi$Ą;

.field public static final enum ċ:Lo/pi$Ą;

.field public static final enum đ:Lo/pi$Ą;

.field public static final enum Ē:Lo/pi$Ą;

.field public static final enum ē:Lo/pi$Ą;

.field public static final enum Ė:Lo/pi$Ą;

.field public static final enum ė:Lo/pi$Ą;

.field public static final enum Ę:Lo/pi$Ą;

.field public static final enum ę:Lo/pi$Ą;

.field public static final enum ġ:Lo/pi$Ą;

.field private static final synthetic ģ:[Lo/pi$Ą;

.field public static final enum ȃ:Lo/pi$Ą;

.field public static final enum Ȋ:Lo/pi$Ą;

.field public static final enum Ƞ:Lo/pi$Ą;

.field public static final enum ˮ͈:Lo/pi$Ą;

.field public static final enum ˮ͍:Lo/pi$Ą;

.field public static final enum ܕ:Lo/pi$Ą;

.field public static final enum ܨ:Lo/pi$Ą;

.field public static final enum ঽ্:Lo/pi$Ą;

.field public static final enum 㥳:Lo/pi$Ą;

.field public static final enum 㱽:Lo/pi$Ą;

.field public static final enum 㵼:Lo/pi$Ą;

.field public static final enum 䒧:Lo/pi$Ą;

.field public static final enum 囃:Lo/pi$Ą;

.field public static final enum 岱:Lo/pi$Ą;

.field public static final enum 庸:Lo/pi$Ą;

.field public static final enum 廂:Lo/pi$Ą;

.field public static final enum 廅:Lo/pi$Ą;

.field public static final enum 櫯:Lo/pi$Ą;

.field public static final enum 纫:Lo/pi$Ą;

.field public static final enum 躆:Lo/pi$Ą;

.field public static final enum 鷭:Lo/pi$Ą;

.field public static final enum 띥:Lo/pi$Ą;


# direct methods
.method static <clinit>()V
    .locals 3

    new-instance v0, Lo/pi$Ą;

    const-string v1, "MOVE"

    const/4 v2, 0x0

    invoke-direct {v0, v1, v2}, Lo/pi$Ą;-><init>(Ljava/lang/String;I)V

    sput-object v0, Lo/pi$Ą;->鷭:Lo/pi$Ą;

    new-instance v0, Lo/pi$Ą;

    const-string v1, "LOADK"

    const/4 v2, 0x1

    invoke-direct {v0, v1, v2}, Lo/pi$Ą;-><init>(Ljava/lang/String;I)V

    sput-object v0, Lo/pi$Ą;->櫯:Lo/pi$Ą;

    new-instance v0, Lo/pi$Ą;

    const-string v1, "LOADBOOL"

    const/4 v2, 0x2

    invoke-direct {v0, v1, v2}, Lo/pi$Ą;-><init>(Ljava/lang/String;I)V

    sput-object v0, Lo/pi$Ą;->ˮ͈:Lo/pi$Ą;

    new-instance v0, Lo/pi$Ą;

    const-string v1, "LOADNIL"

    const/4 v2, 0x3

    invoke-direct {v0, v1, v2}, Lo/pi$Ą;-><init>(Ljava/lang/String;I)V

    sput-object v0, Lo/pi$Ą;->ȃ:Lo/pi$Ą;

    new-instance v0, Lo/pi$Ą;

    const-string v1, "GETUPVAL"

    const/4 v2, 0x4

    invoke-direct {v0, v1, v2}, Lo/pi$Ą;-><init>(Ljava/lang/String;I)V

    sput-object v0, Lo/pi$Ą;->Ą:Lo/pi$Ą;

    new-instance v0, Lo/pi$Ą;

    const-string v1, "GETGLOBAL"

    const/4 v2, 0x5

    invoke-direct {v0, v1, v2}, Lo/pi$Ą;-><init>(Ljava/lang/String;I)V

    sput-object v0, Lo/pi$Ą;->ą:Lo/pi$Ą;

    new-instance v0, Lo/pi$Ą;

    const-string v1, "GETTABLE"

    const/4 v2, 0x6

    invoke-direct {v0, v1, v2}, Lo/pi$Ą;-><init>(Ljava/lang/String;I)V

    sput-object v0, Lo/pi$Ą;->Ć:Lo/pi$Ą;

    new-instance v0, Lo/pi$Ą;

    const-string v1, "SETGLOBAL"

    const/4 v2, 0x7

    invoke-direct {v0, v1, v2}, Lo/pi$Ą;-><init>(Ljava/lang/String;I)V

    sput-object v0, Lo/pi$Ą;->ć:Lo/pi$Ą;

    new-instance v0, Lo/pi$Ą;

    const-string v1, "SETUPVAL"

    const/16 v2, 0x8

    invoke-direct {v0, v1, v2}, Lo/pi$Ą;-><init>(Ljava/lang/String;I)V

    sput-object v0, Lo/pi$Ą;->ˮ͍:Lo/pi$Ą;

    new-instance v0, Lo/pi$Ą;

    const-string v1, "SETTABLE"

    const/16 v2, 0x9

    invoke-direct {v0, v1, v2}, Lo/pi$Ą;-><init>(Ljava/lang/String;I)V

    sput-object v0, Lo/pi$Ą;->岱:Lo/pi$Ą;

    new-instance v0, Lo/pi$Ą;

    const-string v1, "NEWTABLE"

    const/16 v2, 0xa

    invoke-direct {v0, v1, v2}, Lo/pi$Ą;-><init>(Ljava/lang/String;I)V

    sput-object v0, Lo/pi$Ą;->Ȋ:Lo/pi$Ą;

    new-instance v0, Lo/pi$Ą;

    const-string v1, "SELF"

    const/16 v2, 0xb

    invoke-direct {v0, v1, v2}, Lo/pi$Ą;-><init>(Ljava/lang/String;I)V

    sput-object v0, Lo/pi$Ą;->ċ:Lo/pi$Ą;

    new-instance v0, Lo/pi$Ą;

    const-string v1, "ADD"

    const/16 v2, 0xc

    invoke-direct {v0, v1, v2}, Lo/pi$Ą;-><init>(Ljava/lang/String;I)V

    sput-object v0, Lo/pi$Ą;->纫:Lo/pi$Ą;

    new-instance v0, Lo/pi$Ą;

    const-string v1, "SUB"

    const/16 v2, 0xd

    invoke-direct {v0, v1, v2}, Lo/pi$Ą;-><init>(Ljava/lang/String;I)V

    sput-object v0, Lo/pi$Ą;->䒧:Lo/pi$Ą;

    new-instance v0, Lo/pi$Ą;

    const-string v1, "MUL"

    const/16 v2, 0xe

    invoke-direct {v0, v1, v2}, Lo/pi$Ą;-><init>(Ljava/lang/String;I)V

    sput-object v0, Lo/pi$Ą;->躆:Lo/pi$Ą;

    new-instance v0, Lo/pi$Ą;

    const-string v1, "DIV"

    const/16 v2, 0xf

    invoke-direct {v0, v1, v2}, Lo/pi$Ą;-><init>(Ljava/lang/String;I)V

    sput-object v0, Lo/pi$Ą;->ܕ:Lo/pi$Ą;

    new-instance v0, Lo/pi$Ą;

    const-string v1, "POW"

    const/16 v2, 0x10

    invoke-direct {v0, v1, v2}, Lo/pi$Ą;-><init>(Ljava/lang/String;I)V

    sput-object v0, Lo/pi$Ą;->庸:Lo/pi$Ą;

    new-instance v0, Lo/pi$Ą;

    const-string v1, "UNM"

    const/16 v2, 0x11

    invoke-direct {v0, v1, v2}, Lo/pi$Ą;-><init>(Ljava/lang/String;I)V

    sput-object v0, Lo/pi$Ą;->đ:Lo/pi$Ą;

    new-instance v0, Lo/pi$Ą;

    const-string v1, "NOT"

    const/16 v2, 0x12

    invoke-direct {v0, v1, v2}, Lo/pi$Ą;-><init>(Ljava/lang/String;I)V

    sput-object v0, Lo/pi$Ą;->Ē:Lo/pi$Ą;

    new-instance v0, Lo/pi$Ą;

    const-string v1, "CONCAT"

    const/16 v2, 0x13

    invoke-direct {v0, v1, v2}, Lo/pi$Ą;-><init>(Ljava/lang/String;I)V

    sput-object v0, Lo/pi$Ą;->ē:Lo/pi$Ą;

    new-instance v0, Lo/pi$Ą;

    const-string v1, "JMP"

    const/16 v2, 0x14

    invoke-direct {v0, v1, v2}, Lo/pi$Ą;-><init>(Ljava/lang/String;I)V

    sput-object v0, Lo/pi$Ą;->띥:Lo/pi$Ą;

    new-instance v0, Lo/pi$Ą;

    const-string v1, "EQ"

    const/16 v2, 0x15

    invoke-direct {v0, v1, v2}, Lo/pi$Ą;-><init>(Ljava/lang/String;I)V

    sput-object v0, Lo/pi$Ą;->㥳:Lo/pi$Ą;

    new-instance v0, Lo/pi$Ą;

    const-string v1, "LT"

    const/16 v2, 0x16

    invoke-direct {v0, v1, v2}, Lo/pi$Ą;-><init>(Ljava/lang/String;I)V

    sput-object v0, Lo/pi$Ą;->Ė:Lo/pi$Ą;

    new-instance v0, Lo/pi$Ą;

    const-string v1, "LE"

    const/16 v2, 0x17

    invoke-direct {v0, v1, v2}, Lo/pi$Ą;-><init>(Ljava/lang/String;I)V

    sput-object v0, Lo/pi$Ą;->ė:Lo/pi$Ą;

    new-instance v0, Lo/pi$Ą;

    const-string v1, "TEST"

    const/16 v2, 0x18

    invoke-direct {v0, v1, v2}, Lo/pi$Ą;-><init>(Ljava/lang/String;I)V

    sput-object v0, Lo/pi$Ą;->Ę:Lo/pi$Ą;

    new-instance v0, Lo/pi$Ą;

    const-string v1, "CALL"

    const/16 v2, 0x19

    invoke-direct {v0, v1, v2}, Lo/pi$Ą;-><init>(Ljava/lang/String;I)V

    sput-object v0, Lo/pi$Ą;->ę:Lo/pi$Ą;

    new-instance v0, Lo/pi$Ą;

    const-string v1, "TAILCALL"

    const/16 v2, 0x1a

    invoke-direct {v0, v1, v2}, Lo/pi$Ą;-><init>(Ljava/lang/String;I)V

    sput-object v0, Lo/pi$Ą;->廂:Lo/pi$Ą;

    new-instance v0, Lo/pi$Ą;

    const-string v1, "RETURN"

    const/16 v2, 0x1b

    invoke-direct {v0, v1, v2}, Lo/pi$Ą;-><init>(Ljava/lang/String;I)V

    sput-object v0, Lo/pi$Ą;->囃:Lo/pi$Ą;

    new-instance v0, Lo/pi$Ą;

    const-string v1, "FORLOOP"

    const/16 v2, 0x1c

    invoke-direct {v0, v1, v2}, Lo/pi$Ą;-><init>(Ljava/lang/String;I)V

    sput-object v0, Lo/pi$Ą;->ঽ্:Lo/pi$Ą;

    new-instance v0, Lo/pi$Ą;

    const-string v1, "TFORLOOP"

    const/16 v2, 0x1d

    invoke-direct {v0, v1, v2}, Lo/pi$Ą;-><init>(Ljava/lang/String;I)V

    sput-object v0, Lo/pi$Ą;->廅:Lo/pi$Ą;

    new-instance v0, Lo/pi$Ą;

    const-string v1, "TFORPREP"

    const/16 v2, 0x1e

    invoke-direct {v0, v1, v2}, Lo/pi$Ą;-><init>(Ljava/lang/String;I)V

    sput-object v0, Lo/pi$Ą;->㵼:Lo/pi$Ą;

    new-instance v0, Lo/pi$Ą;

    const-string v1, "SETLIST"

    const/16 v2, 0x1f

    invoke-direct {v0, v1, v2}, Lo/pi$Ą;-><init>(Ljava/lang/String;I)V

    sput-object v0, Lo/pi$Ą;->㱽:Lo/pi$Ą;

    new-instance v0, Lo/pi$Ą;

    const-string v1, "SETLISTO"

    const/16 v2, 0x20

    invoke-direct {v0, v1, v2}, Lo/pi$Ą;-><init>(Ljava/lang/String;I)V

    sput-object v0, Lo/pi$Ą;->Ƞ:Lo/pi$Ą;

    new-instance v0, Lo/pi$Ą;

    const-string v1, "CLOSE"

    const/16 v2, 0x21

    invoke-direct {v0, v1, v2}, Lo/pi$Ą;-><init>(Ljava/lang/String;I)V

    sput-object v0, Lo/pi$Ą;->ġ:Lo/pi$Ą;

    new-instance v0, Lo/pi$Ą;

    const-string v1, "CLOSURE"

    const/16 v2, 0x22

    invoke-direct {v0, v1, v2}, Lo/pi$Ą;-><init>(Ljava/lang/String;I)V

    sput-object v0, Lo/pi$Ą;->ܨ:Lo/pi$Ą;

    const/16 v0, 0x23

    new-array v0, v0, [Lo/pi$Ą;

    sget-object v1, Lo/pi$Ą;->鷭:Lo/pi$Ą;

    const/4 v2, 0x0

    aput-object v1, v0, v2

    sget-object v1, Lo/pi$Ą;->櫯:Lo/pi$Ą;

    const/4 v2, 0x1

    aput-object v1, v0, v2

    sget-object v1, Lo/pi$Ą;->ˮ͈:Lo/pi$Ą;

    const/4 v2, 0x2

    aput-object v1, v0, v2

    sget-object v1, Lo/pi$Ą;->ȃ:Lo/pi$Ą;

    const/4 v2, 0x3

    aput-object v1, v0, v2

    sget-object v1, Lo/pi$Ą;->Ą:Lo/pi$Ą;

    const/4 v2, 0x4

    aput-object v1, v0, v2

    sget-object v1, Lo/pi$Ą;->ą:Lo/pi$Ą;

    const/4 v2, 0x5

    aput-object v1, v0, v2

    sget-object v1, Lo/pi$Ą;->Ć:Lo/pi$Ą;

    const/4 v2, 0x6

    aput-object v1, v0, v2

    sget-object v1, Lo/pi$Ą;->ć:Lo/pi$Ą;

    const/4 v2, 0x7

    aput-object v1, v0, v2

    sget-object v1, Lo/pi$Ą;->ˮ͍:Lo/pi$Ą;

    const/16 v2, 0x8

    aput-object v1, v0, v2

    sget-object v1, Lo/pi$Ą;->岱:Lo/pi$Ą;

    const/16 v2, 0x9

    aput-object v1, v0, v2

    sget-object v1, Lo/pi$Ą;->Ȋ:Lo/pi$Ą;

    const/16 v2, 0xa

    aput-object v1, v0, v2

    sget-object v1, Lo/pi$Ą;->ċ:Lo/pi$Ą;

    const/16 v2, 0xb

    aput-object v1, v0, v2

    sget-object v1, Lo/pi$Ą;->纫:Lo/pi$Ą;

    const/16 v2, 0xc

    aput-object v1, v0, v2

    sget-object v1, Lo/pi$Ą;->䒧:Lo/pi$Ą;

    const/16 v2, 0xd

    aput-object v1, v0, v2

    sget-object v1, Lo/pi$Ą;->躆:Lo/pi$Ą;

    const/16 v2, 0xe

    aput-object v1, v0, v2

    sget-object v1, Lo/pi$Ą;->ܕ:Lo/pi$Ą;

    const/16 v2, 0xf

    aput-object v1, v0, v2

    sget-object v1, Lo/pi$Ą;->庸:Lo/pi$Ą;

    const/16 v2, 0x10

    aput-object v1, v0, v2

    sget-object v1, Lo/pi$Ą;->đ:Lo/pi$Ą;

    const/16 v2, 0x11

    aput-object v1, v0, v2

    sget-object v1, Lo/pi$Ą;->Ē:Lo/pi$Ą;

    const/16 v2, 0x12

    aput-object v1, v0, v2

    sget-object v1, Lo/pi$Ą;->ē:Lo/pi$Ą;

    const/16 v2, 0x13

    aput-object v1, v0, v2

    sget-object v1, Lo/pi$Ą;->띥:Lo/pi$Ą;

    const/16 v2, 0x14

    aput-object v1, v0, v2

    sget-object v1, Lo/pi$Ą;->㥳:Lo/pi$Ą;

    const/16 v2, 0x15

    aput-object v1, v0, v2

    sget-object v1, Lo/pi$Ą;->Ė:Lo/pi$Ą;

    const/16 v2, 0x16

    aput-object v1, v0, v2

    sget-object v1, Lo/pi$Ą;->ė:Lo/pi$Ą;

    const/16 v2, 0x17

    aput-object v1, v0, v2

    sget-object v1, Lo/pi$Ą;->Ę:Lo/pi$Ą;

    const/16 v2, 0x18

    aput-object v1, v0, v2

    sget-object v1, Lo/pi$Ą;->ę:Lo/pi$Ą;

    const/16 v2, 0x19

    aput-object v1, v0, v2

    sget-object v1, Lo/pi$Ą;->廂:Lo/pi$Ą;

    const/16 v2, 0x1a

    aput-object v1, v0, v2

    sget-object v1, Lo/pi$Ą;->囃:Lo/pi$Ą;

    const/16 v2, 0x1b

    aput-object v1, v0, v2

    sget-object v1, Lo/pi$Ą;->ঽ্:Lo/pi$Ą;

    const/16 v2, 0x1c

    aput-object v1, v0, v2

    sget-object v1, Lo/pi$Ą;->廅:Lo/pi$Ą;

    const/16 v2, 0x1d

    aput-object v1, v0, v2

    sget-object v1, Lo/pi$Ą;->㵼:Lo/pi$Ą;

    const/16 v2, 0x1e

    aput-object v1, v0, v2

    sget-object v1, Lo/pi$Ą;->㱽:Lo/pi$Ą;

    const/16 v2, 0x1f

    aput-object v1, v0, v2

    sget-object v1, Lo/pi$Ą;->Ƞ:Lo/pi$Ą;

    const/16 v2, 0x20

    aput-object v1, v0, v2

    sget-object v1, Lo/pi$Ą;->ġ:Lo/pi$Ą;

    const/16 v2, 0x21

    aput-object v1, v0, v2

    sget-object v1, Lo/pi$Ą;->ܨ:Lo/pi$Ą;

    const/16 v2, 0x22

    aput-object v1, v0, v2

    sput-object v0, Lo/pi$Ą;->ģ:[Lo/pi$Ą;

    return-void
.end method

.method private constructor <init>(Ljava/lang/String;I)V
    .locals 0

    invoke-direct {p0, p1, p2}, Ljava/lang/Enum;-><init>(Ljava/lang/String;I)V

    return-void
.end method

.method public static valueOf(Ljava/lang/String;)Lo/pi$Ą;
    .locals 1

    const-class v0, Lo/pi$Ą;

    invoke-static {v0, p0}, Ljava/lang/Enum;->valueOf(Ljava/lang/Class;Ljava/lang/String;)Ljava/lang/Enum;

    move-result-object v0

    check-cast v0, Lo/pi$Ą;

    return-object v0
.end method

.method public static values()[Lo/pi$Ą;
    .locals 5

    sget-object v0, Lo/pi$Ą;->ģ:[Lo/pi$Ą;

    move-object v3, v0

    array-length v3, v3

    new-array v4, v3, [Lo/pi$Ą;

    const/4 v1, 0x0

    const/4 v2, 0x0

    invoke-static {v0, v1, v4, v2, v3}, Ljava/lang/System;->arraycopy(Ljava/lang/Object;ILjava/lang/Object;II)V

    return-object v4
.end method
